msaFileWorker/__init__.py
msaFileWorker/utils/__init__.py
msaFileWorker/utils/constans.py
msaFileWorker/utils/file_worker.py
msafileworker-0.0.8.dist-info/METADATA
msafileworker-0.0.8.dist-info/WHEEL
msafileworker-0.0.8.dist-info/RECORD
