Metadata-Version: 2.1
Name: msaFileWorker
Version: 0.0.8
Summary: Package for work with file system.
Author: Stefan Welcker
Requires-Python: >=3.10.0,<3.11
Classifier: Programming Language :: Python :: 3
Classifier: Programming Language :: Python :: 3.10
Requires-Dist: msaBase (>=0.0.115,<0.1.0)
Requires-Dist: msaFileSystem (==0.0.8)
